[{"id":128,"title":"Bagaimana cara membuat blog menggunakan API di Github","date":"2018-3-26 22:23:59","text":"Lorem ipsum dolor sit amet, consectetur adipisicing elit. Vitae veritatis repudiandae in quam itaque nobis expedita facere harum fuga cum. Reprehenderit nulla optio ex tenetur debitis qui aperiam, maxime eum!","snonce":1522077839917},{"id":127,"title":"Bagaimana cara membuat blog menggunakan API di Github","date":"2018-3-26 22:23:59","text":"Lorem ipsum dolor sit amet, consectetur adipisicing elit. Vitae veritatis repudiandae in quam itaque nobis expedita facere harum fuga cum. Reprehenderit nulla optio ex tenetur debitis qui aperiam, maxime eum!","snonce":1522077839917}]